README.rst
setup.py
dork/__init__.py
dork/config.py
dork/dns.py
dork/docker.py
dork/dork.py
dork/git.py
dork/matcher.py
dork/runner.py
dork.egg-info/PKG-INFO
dork.egg-info/SOURCES.txt
dork.egg-info/dependency_links.txt
dork.egg-info/entry_points.txt
dork.egg-info/requires.txt
dork.egg-info/top_level.txt
dork/services/__init__.py
dork/services/dns.py
dork/services/proxy.py