Metadata-Version: 1.1
Name: dork
Version: 0.2.3
Summary: Docker and ansible based development containers.
Home-page: https://github.com/iamdork/dork
Author: Philipp Melab
Author-email: philipp.melab@gmail.com
License: MIT
Download-URL: https://github.com/iamdork/dork/tarball/0.1.6
Keywords: docker devops development ansible
Platform: UNKNOWN
Classifier: Development Status :: 3 - Alpha
Classifier: Intended Audience :: Developers
Classifier: Topic :: Software Development :: Build Tools
Classifier: License :: OSI Approved :: MIT License
Classifier: Programming Language :: Python :: 2.6
Classifier: Programming Language :: Python :: 2.7
